WeatherData/__init__.py
WeatherData/fcst.py
WeatherData/obs.py
WeatherData/region_code.py
WeatherData/util.py
WeatherData-0.0.21.dist-info/LICENSE
WeatherData-0.0.21.dist-info/METADATA
WeatherData-0.0.21.dist-info/WHEEL
WeatherData-0.0.21.dist-info/top_level.txt
WeatherData-0.0.21.dist-info/RECORD
