Metadata-Version: 2.1
Name: WeatherData
Version: 0.0.21
Summary: Get weather data
Home-page: https://github.com/cloudybay/weatherdata-sdk
Author: CloudyBay
Author-email: cibi@cloudybay.com.tw
License: UNKNOWN
Keywords: weather,forecast,observation,taiwan
Platform: UNKNOWN
Classifier: Programming Language :: Python :: 3
Classifier: License :: OSI Approved :: MIT License
Classifier: Operating System :: OS Independent
Requires-Python: >=3.6
License-File: LICENSE
Requires-Dist: pytz
Requires-Dist: requests
Requires-Dist: urllib3
